manager/__init__.py
manager/config.py
manager/connection.py
manager/system.py
manager/templates.py
manager/ui.py
manager/commands/__init__.py
manager/commands/conda.py
manager/commands/files.py
manager/commands/help.py
manager/commands/job_templates.py
manager/commands/logs.py
manager/commands/modules.py
manager/commands/resources.py
manager/commands/settings.py
manager/commands/slurm.py
manager/commands/tunnel.py
manager/ui/__init__.py
manager/ui/conda_manager.py
manager/ui/file_manager.py
manager/ui/help_menu.py
manager/ui/interactive.py
manager/ui/job_dashboard.py
manager/ui/job_templates.py
manager/ui/logs_menu.py
manager/ui/menus.py
manager/ui/modules_menu.py
manager/ui/quota.py
manager/ui/resources.py
manager/ui/settings_menu.py
manager/ui/styles.py
manager/ui/tunnel_menu.py
paramtui-0.1.2.dist-info/METADATA
paramtui-0.1.2.dist-info/WHEEL
paramtui-0.1.2.dist-info/entry_points.txt
paramtui-0.1.2.dist-info/top_level.txt
paramtui-0.1.2.dist-info/RECORD
