Metadata-Version: 2.4
Name: paramtui
Version: 0.1.2
Summary: A modern terminal user interface for managing HPC clusters via SSH
Author: Ayush Saxena
License: MIT
Project-URL: Homepage, https://github.com/ayush1512/ParamTUI
Project-URL: Repository, https://github.com/ayush1512/ParamTUI
Project-URL: Bug Tracker, https://github.com/ayush1512/ParamTUI/issues
Keywords: ssh,hpc,tui,terminal,cluster,slurm,param
Classifier: Development Status :: 3 - Alpha
Classifier: Intended Audience :: Developers
Classifier: Intended Audience :: System Administrators
Classifier: License :: OSI Approved :: MIT License
Classifier: Programming Language :: Python :: 3
Classifier: Programming Language :: Python :: 3.8
Classifier: Programming Language :: Python :: 3.9
Classifier: Programming Language :: Python :: 3.10
Classifier: Programming Language :: Python :: 3.11
Classifier: Programming Language :: Python :: 3.12
Classifier: Topic :: Terminals
Requires-Python: >=3.8
Requires-Dist: questionary>=2.0.0
Requires-Dist: rich>=13.0.0
